ambiverseclient/__init__.py
ambiverseclient/clients.py
ambiverseclient/models.py
ambiverseclient-0.3.dist-info/LICENSE
ambiverseclient-0.3.dist-info/METADATA
ambiverseclient-0.3.dist-info/WHEEL
ambiverseclient-0.3.dist-info/top_level.txt
ambiverseclient-0.3.dist-info/RECORD
