Metadata-Version: 2.1
Name: ambiverseclient
Version: 0.3
Summary: UNKNOWN
Home-page: UNKNOWN
Author: Linus Kohl
Author-email: linus@munichresearch.com
License: GPLv3
Platform: UNKNOWN
Requires-Python: >=3.7
Requires-Dist: requests
Requires-Dist: marshmallow (>=3.0.0rc4)
